{
	"info": {
		"_postman_id": "26420a7a-a1cd-442f-bd60-41e0f503dd52",
		"name": "LiveLIVE",
		"schema": "https://schema.getpostman.com/json/collection/v2.1.0/collection.json"
	},
	"item": [
		{
			"name": "streamDetails",
			"request": {
				"method": "GET",
				"header": [
					{
						"key": "X-API-Key",
						"value": "40-af-57-0d-2d-f2-ca-fc-0b-af-0f-f7-3f-73-97-0d",
						"type": "text"
					}
				],
				"url": {
					"raw": "https://api.liveswitch.io/ApplicationConfigs",
					"protocol": "https",
					"host": [
						"api",
						"liveswitch",
						"io"
					],
					"path": [
						"ApplicationConfigs"
					]
				}
			},
			"response": []
		}
	],
	"protocolProfileBehavior": {}
}